jflib/__init__.py
jflib/argparser_to_readme.py
jflib/capturing.py
jflib/command_watcher.py
jflib/config_reader.py
jflib/icinga.py
jflib/send_email.py
jflib/termcolor.py
jflib/utils.py
jflib-1.0.0.dist-info/LICENSE
jflib-1.0.0.dist-info/WHEEL
jflib-1.0.0.dist-info/METADATA
jflib-1.0.0.dist-info/RECORD
